{
  "operationId": "get-protocol-trending-tokens",
  "summary": "",
  "tags": [
    "wormholescan"
  ],
  "method": "GET",
  "path": "/api/v1/protocols/{protocolId}/trending_tokens",
  "parameters": [
    {
      "name": "protocolId",
      "in": "path",
      "required": true,
      "type": "string"
    },
    {
      "name": "from",
      "in": "query",
      "required": true,
      "type": "string"
    },
    {
      "name": "to",
      "in": "query",
      "required": true,
      "type": "string"
    }
  ],
  "responses": {
    "200": {
      "description": "OK",
      "schema": {
        "$ref": "#/definitions/protocols.ProtocolTrendingTokensResponse"
      }
    },
    "400": {
      "description": "Bad Request",
      "schema": {
        "$ref": "#/definitions/response.APIError"
      }
    },
    "500": {
      "description": "Internal Server Error",
      "schema": {
        "$ref": "#/definitions/response.APIError"
      }
    }
  }
}